acore_constants/__init__.py
acore_constants/_version.py
acore_constants/api.py
acore_constants/constants.py
acore_constants/paths.py
acore_constants/docs/__init__.py
acore_constants-0.3.1.dist-info/AUTHORS.rst
acore_constants-0.3.1.dist-info/LICENSE.txt
acore_constants-0.3.1.dist-info/METADATA
acore_constants-0.3.1.dist-info/WHEEL
acore_constants-0.3.1.dist-info/top_level.txt
acore_constants-0.3.1.dist-info/RECORD
